meg_runtime/__init__.py
meg_runtime/__main__.py
meg_runtime/app.py
meg_runtime/config.py
meg_runtime/logger.py
meg_runtime/git/__init__.py
meg_runtime/git/lockFile.py
meg_runtime/git/locking.py
meg_runtime/git/manager.py
meg_runtime/git/permissions.py
meg_runtime/git/repository.py
meg_runtime/plugins/__init__.py
meg_runtime/plugins/manager.py
meg_runtime/plugins/plugin.py
meg_runtime/ui/__init__.py
meg_runtime/ui/addpluginpanel.py
meg_runtime/ui/addpluginpanel.ui
meg_runtime/ui/basepanel.py
meg_runtime/ui/clonepanel.py
meg_runtime/ui/clonepanel.ui
meg_runtime/ui/filechooser.py
meg_runtime/ui/helpers.py
meg_runtime/ui/mainpanel.py
meg_runtime/ui/mainpanel.ui
meg_runtime/ui/mainwindow.ui
meg_runtime/ui/manager.py
meg_runtime/ui/pluginspanel.py
meg_runtime/ui/pluginspanel.ui
meg_runtime/ui/preferencespanel.py
meg_runtime/ui/preferencespanel.ui
meg_runtime/ui/repopanel.py
meg_runtime/ui/repopanel.ui
meg_runtime/ui/roleeditpanel.py
meg_runtime/ui/roleeditpanel.ui
meg_runtime/ui/rolespanel.py
meg_runtime/ui/rolespanel.ui
meg_runtime/ui/webpanel.py
meg_runtime/ui/images/clone.svg
meg_runtime/ui/images/clonepanel.svg
meg_runtime/ui/images/folder-open.svg
meg_runtime/ui/images/git.svg
meg_runtime/ui/images/plugins.svg
meg_runtime/ui/images/pluginspanel.svg
meg_runtime/ui/images/preferences.svg
meg_runtime/ui/images/preferencespanel.svg
meg_runtime/ui/images/repopanel.svg
meg_runtime/ui/images/roles.svg
meg_runtime/ui/images/user.svg
meg_runtime/ui/images/users.svg
meg_runtime-0.0.16.dist-info/LICENSE
meg_runtime-0.0.16.dist-info/METADATA
meg_runtime-0.0.16.dist-info/WHEEL
meg_runtime-0.0.16.dist-info/top_level.txt
meg_runtime-0.0.16.dist-info/RECORD
