Metadata-Version: 2.1
Name: meg-runtime
Version: 0.0.16
Summary: Multimedia Extensible Git Runtime Library
Home-page: https://github.com/MultimediaExtensibleGit/Runtime
Author: Multimedia Extensible Git
Author-email: kyletpugh@users.noreply.github.com
License: MIT
Platform: any
Classifier: Programming Language :: Python :: 3
Classifier: License :: OSI Approved :: MIT License
Classifier: Operating System :: OS Independent
Requires-Python: >=3.7
Requires-Dist: PyQt5
Requires-Dist: PyQtWebEngine
Requires-Dist: pillow
Requires-Dist: pygit2
Requires-Dist: python-dateutil
Requires-Dist: requests
Requires-Dist: pywin32 ; os_name == "nt"
